bar_chart_race_cn/__init__.py
bar_chart_race_cn/_colormaps.py
bar_chart_race_cn/_make_chart.py
bar_chart_race_cn-0.11.dist-info/METADATA
bar_chart_race_cn-0.11.dist-info/WHEEL
bar_chart_race_cn-0.11.dist-info/top_level.txt
bar_chart_race_cn-0.11.dist-info/RECORD
