Metadata-Version: 2.1
Name: bar-chart-race-cn
Version: 0.11
Summary: 解决bar_chart_race无法显示中文的问题
Home-page: https://github.com/thunderhit/bar_chart_race_cn
Author: thunderhit
Author-email: thunderhit@qq.com
License: MIT
Keywords: bar chart race,支持中文
Platform: UNKNOWN
Requires-Python: >=3.5
Requires-Dist: matplotlib
Requires-Dist: numpy
Requires-Dist: pandas
